Metadata-Version: 2.1
Name: python-requests-anonymous-session
Version: 1.0.2
Summary: Randomizes the user agent, along with default headers found with that browser as well as the cipher suite used.
Home-page: https://github.com/NoahCardoza/python-requests-anonymous-session
Author: Noah Cardoza
Author-email: noahcardoza@gmail.com
License: UNKNOWN
Platform: UNKNOWN
Classifier: Programming Language :: Python :: 3
Classifier: Operating System :: OS Independent
License-File: LICENSE
